forta/__init__.py
forta/__main__.py
forta/auth/__init__.py
forta/auth/core.py
forta/enum.py
forta/fastapi.py
forta/httpx.py
forta/lk/__init__.py
forta/lk/core.py
forta/odata/__init__.py
forta/odata/core.py
forta/payout/__init__.py
forta/payout/core.py
forta_gate-0.1.0.dist-info/METADATA
forta_gate-0.1.0.dist-info/WHEEL
forta_gate-0.1.0.dist-info/entry_points.txt
forta_gate-0.1.0.dist-info/RECORD
