Metadata-Version: 2.1
Name: forta-gate
Version: 0.1.0
Summary: 
Author: Anton Rastyazhenko
Author-email: rastyazhenko.anton@gmail.com
Requires-Python: >=3.11,<4.0
Classifier: Programming Language :: Python :: 3
Classifier: Programming Language :: Python :: 3.11
Requires-Dist: fastapi (>=0.103.2,<0.104.0)
Requires-Dist: nicegui[netifaces] (>=1.3.17,<2.0.0)
Requires-Dist: pybrom (>=1.1.6)
Requires-Dist: pydantic-settings (>=2.0.3)
Requires-Dist: pytest (>=7.4.2,<8.0.0)
Requires-Dist: trio (>=0.22.2,<0.23.0)
Requires-Dist: typer-config[all] (>=1.2.1)
Requires-Dist: typer[all] (>=0.9.0)
